README.rst
setup.py
cases/__init__.py
cases/casegen.py
cases.egg-info/PKG-INFO
cases.egg-info/SOURCES.txt
cases.egg-info/dependency_links.txt
cases.egg-info/requires.txt
cases.egg-info/top_level.txt